.bzrignore
CHANGES.txt
COPYRIGHT.txt
LICENSE.txt
README.txt
setup.py
Products/__init__.py
Products.Zelenium.egg-info/PKG-INFO
Products.Zelenium.egg-info/SOURCES.txt
Products.Zelenium.egg-info/dependency_links.txt
Products.Zelenium.egg-info/entry_points.txt
Products.Zelenium.egg-info/namespace_packages.txt
Products.Zelenium.egg-info/not-zip-safe
Products.Zelenium.egg-info/requires.txt
Products.Zelenium.egg-info/top_level.txt
Products/Zelenium/__init__.py
Products/Zelenium/configure.zcml
Products/Zelenium/exclude.txt
Products/Zelenium/generator.py
Products/Zelenium/interfaces.py
Products/Zelenium/permissions.py
Products/Zelenium/version.txt
Products/Zelenium/zuite.py
Products/Zelenium/scripts/startWebServer.bat
Products/Zelenium/scripts/stopWebServer.bat
Products/Zelenium/scripts/tinyWebClient.py
Products/Zelenium/scripts/tinyWebServer.py
Products/Zelenium/selenium/.objects
Products/Zelenium/selenium/COPYRIGHT.txt
Products/Zelenium/selenium/VERSION.txt
Products/Zelenium/selenium/coding-conventions.txt
Products/Zelenium/selenium/index.html
Products/Zelenium/selenium/install-readme.txt
Products/Zelenium/selenium/readyState.xpi
Products/Zelenium/selenium/reference.html
Products/Zelenium/selenium/META-INF/MANIFEST.MF
Products/Zelenium/selenium/META-INF/maven/org.openqa.selenium.core/selenium-core/pom.properties
Products/Zelenium/selenium/META-INF/maven/org.openqa.selenium.core/selenium-core/pom.xml
Products/Zelenium/selenium/core/Blank.html
Products/Zelenium/selenium/core/InjectedRemoteRunner.html
Products/Zelenium/selenium/core/RemoteRunner.html
Products/Zelenium/selenium/core/SeleniumLog.html
Products/Zelenium/selenium/core/TestPrompt.html
Products/Zelenium/selenium/core/TestRunner-splash.html
Products/Zelenium/selenium/core/TestRunner.hta
Products/Zelenium/selenium/core/TestRunner.html
Products/Zelenium/selenium/core/iedoc-core.xml
Products/Zelenium/selenium/core/iedoc.xml
Products/Zelenium/selenium/core/selenium-logo.png
Products/Zelenium/selenium/core/selenium-test.css
Products/Zelenium/selenium/core/selenium.css
Products/Zelenium/selenium/core/domviewer/butmin.gif
Products/Zelenium/selenium/core/domviewer/butplus.gif
Products/Zelenium/selenium/core/domviewer/domviewer.css
Products/Zelenium/selenium/core/domviewer/domviewer.html
Products/Zelenium/selenium/core/domviewer/selenium-domviewer.js
