Metadata-Version: 1.0
Name: Products.Zelenium
Version: 1.0.1
Summary: Run Selenium test suites from within Zope2
Home-page: http://pypi.python.org/pypi/Products.Zelenium
Author: Tres Seaver
Author-email: tseaver@palladion.com
License: ZPL 2.1
Keywords: selenium zope2
Platform: UNKNOWN
Classifier: Development Status :: 5 - Production/Stable
Classifier: Framework :: Zope2
Classifier: Intended Audience :: Developers
Classifier: License :: OSI Approved :: Zope Public License
Classifier: Programming Language :: Python
Classifier: Topic :: Software Development :: Testing
